{
  "department": "Economics",
  "rows": [
    {
      "classNumber": "12617",
      "courseInstructor": "Robert Mead",
      "siLeader": "Emily Baros",
      "sessionDays": "Mo We",
      "sessionTimes": "2:30-3:45 pm",
      "location": "GH-302"
    },
    {
      "classNumber": "12351",
      "courseInstructor": "Francis Mummery",
      "siLeader": "Joshua Angell",
      "sessionDays": "Tu Th",
      "sessionTimes": "4:00-5:15 pm",
      "location": "GH-304"
    },
    {
      "classNumber": "12711",
      "courseInstructor": "Francis Mummery",
      "siLeader": "Scott Bunal",
      "sessionDays": "Mo We",
      "sessionTimes": "10:00-11:15 am",
      "location": "PLS-255"
    },
    {
      "classNumber": "12108",
      "courseInstructor": "Francis Mummery",
      "siLeader": "Angelica Mora",
      "sessionDays": "Tu Th",
      "sessionTimes": "2:30-3:45 pm",
      "location": "H-321B"
    },
    {
      "classNumber": "12108",
      "courseInstructor": "Francis Mummery",
      "siLeader": "Wanting Yu",
      "sessionDays": "Tu Th",
      "sessionTimes": "11:30-12:45 pm",
      "location": "H-530"
    },
    {
      "classNumber": "12442",
      "courseInstructor": "Kenneth Kim",
      "siLeader": "Li Li",
      "sessionDays": "Mo We",
      "sessionTimes": "10:00-11:15 am",
      "location": "GH-207"
    },
    {
      "classNumber": "21672",
      "courseInstructor": "Kenneth Kim",
      "siLeader": "Jake Herrera",
      "sessionDays": "Mo We",
      "sessionTimes": "1:00-2:15 pm",
      "location": "PLS-255"
    }
  ]
}